server/__init__.py
server/server.py
server/common/__init__.py
server/common/decos.py
server/common/descriptors.py
server/common/errors.py
server/common/metaclasses.py
server/common/utils.py
server/common/variables.py
server/my_server/__init__.py
server/my_server/add_user.py
server/my_server/config_window.py
server/my_server/core.py
server/my_server/database_serv.py
server/my_server/main_window.py
server/my_server/remove_user.py
server/my_server/stat_window.py
mess_server_proj_2023-0.0.1.dist-info/METADATA
mess_server_proj_2023-0.0.1.dist-info/WHEEL
mess_server_proj_2023-0.0.1.dist-info/top_level.txt
mess_server_proj_2023-0.0.1.dist-info/RECORD
